README.md
setup.py
forecaster/__init__.py
forecaster/dataframe.py
forecaster/datareader_wave.py
forecaster/forecaster.py
forecaster/preprocess_rnn.py
forecaster/preprocess_wave.py
forecaster/rnn_data_reader.py
forecaster/rnn_model.py
forecaster/tf_base_model.py
forecaster/tf_utils.py
forecaster.egg-info/PKG-INFO
forecaster.egg-info/SOURCES.txt
forecaster.egg-info/dependency_links.txt
forecaster.egg-info/not-zip-safe
forecaster.egg-info/requires.txt
forecaster.egg-info/top_level.txt