Metadata-Version: 1.0
Name: forecaster
Version: 0.2
Summary: time series forecasting
Home-page: https://github.com/kylinorange/insight/
Author: Jun Xie
Author-email: kylinorange@gmail.com
License: BSD
Platform: UNKNOWN
